uparse_python
