Metadata-Version: 1.1
Name: uparse-python
Version: 0.1.2
Summary: python scripts from UParse
Home-page: https://github.com/zachcp/uparse_python
Author: zach powers
Author-email: zcharlop@rockefeller.edu
License: GPL
Keywords: uparse,usearch,uclust
Platform: UNKNOWN
Classifier: Development Status :: 2 - Pre-Alpha
Classifier: Intended Audience :: Developers
Classifier: Natural Language :: English
Classifier: Programming Language :: Python :: 2.7
